stashapi/__init__.py
stashapi/classes.py
stashapi/log.py
stashapi/marker_parse.py
stashapi/py.typed
stashapi/scrape_parser.py
stashapi/stash_types.py
stashapi/stashapp.py
stashapi/stashbox.py
stashapi/tools.py
stashapi-0.1.3.dist-info/METADATA
stashapi-0.1.3.dist-info/WHEEL
stashapi-0.1.3.dist-info/licenses/LICENSE
stashapi-0.1.3.dist-info/RECORD
