Metadata-Version: 2.4
Name: stashapi
Version: 0.1.3
Summary: API wrapper and tools for interfacing with a [Stash](https://github.com/stashapp/stash) instance
Project-URL: Homepage, https://github.com/stg-annon/stashapi
Author-email: stg-annon <14135675+stg-annon@users.noreply.github.com>
License-Expression: MIT
License-File: LICENSE
Classifier: License :: OSI Approved :: MIT License
Classifier: Programming Language :: Python :: 3.11
Classifier: Programming Language :: Python :: 3.12
Classifier: Programming Language :: Python :: 3.13
Requires-Python: >=3.11
Requires-Dist: requests>=2.32.3
Requires-Dist: typing-extensions>=4.12.2
